<Properties StartupConfiguration="{C8972FD2-6D57-45DE-BDF7-E2982CC80E80}|Default">
  <MonoDevelop.Ide.ItemProperties.InstaGrabb FirstBuild="True" PreferredExecutionTarget="/Applications/Safari.app" />
  <MonoDevelop.Ide.Workbench ActiveDocument="Controllers/WeatherForecastController.cs">
    <Files>
      <File FileName="Controllers/WeatherForecastController.cs" Line="40" Column="1" />
      <File FileName="WeatherForecast.cs" Line="16" Column="1" />
    </Files>
    <Pads>
      <Pad Id="ProjectPad">
        <State name="__root__">
          <Node name="InstaGrabb" expanded="True">
            <Node name="InstaGrabb" expanded="True">
              <Node name="Controllers" expanded="True">
                <Node name="WeatherForecastController.cs" selected="True" />
              </Node>
              <Node name="Properties" expanded="True" />
            </Node>
          </Node>
        </State>
      </Pad>
    </Pads>
  </MonoDevelop.Ide.Workbench>
  <MonoDevelop.Ide.DebuggingService.PinnedWatches />
  <MonoDevelop.Ide.Workspace ActiveConfiguration="Debug" />
  <MonoDevelop.Ide.DebuggingService.Breakpoints>
    <BreakpointStore />
  </MonoDevelop.Ide.DebuggingService.Breakpoints>
  <MultiItemStartupConfigurations />
</Properties>